omero2pandas/__init__.py
omero2pandas/connect.py
omero2pandas/io_tools.py
omero2pandas/remote.py
omero2pandas/upload.py
omero2pandas-0.4.2.dist-info/licenses/LICENSE.txt
omero2pandas-0.4.2.dist-info/METADATA
omero2pandas-0.4.2.dist-info/WHEEL
omero2pandas-0.4.2.dist-info/top_level.txt
omero2pandas-0.4.2.dist-info/RECORD
