Metadata-Version: 2.4
Name: omero2pandas
Version: 0.4.2
Summary: OMERO.tables to pandas bridge
Author-email: "Glencoe Software, Inc." <info@glencoesoftware.com>
License:                     GNU GENERAL PUBLIC LICENSE
Project-URL: github, https://github.com/glencoesoftware/omero2pandas
Classifier: Development Status :: 5 - Production/Stable
Classifier: License :: OSI Approved :: GNU General Public License v3 (GPLv3)
Classifier: Intended Audience :: Science/Research
Classifier: Intended Audience :: Developers
Classifier: Intended Audience :: End Users/Desktop
Classifier: Programming Language :: Python :: 3
Requires-Python: >=3.9
License-File: LICENSE.txt
Requires-Dist: omero-py>=5.19.5
Requires-Dist: pandas>2
Requires-Dist: tqdm
Provides-Extra: token
Requires-Dist: omero-user-token>=0.3.0; extra == "token"
Provides-Extra: remote
Requires-Dist: pyarrow>=19.0.0; extra == "remote"
Requires-Dist: tiledb<0.34.1,>=0.33.2; extra == "remote"
Dynamic: license-file
